CHANGES.txt
README.txt
bootstrap.py
buildout.cfg
setup.py
src/zope/__init__.py
src/zope.app.zptpage.egg-info/PKG-INFO
src/zope.app.zptpage.egg-info/SOURCES.txt
src/zope.app.zptpage.egg-info/dependency_links.txt
src/zope.app.zptpage.egg-info/namespace_packages.txt
src/zope.app.zptpage.egg-info/not-zip-safe
src/zope.app.zptpage.egg-info/requires.txt
src/zope.app.zptpage.egg-info/top_level.txt
src/zope/app/__init__.py
src/zope/app/zptpage/DEPENDENCIES.cfg
src/zope/app/zptpage/PACKAGE.cfg
src/zope/app/zptpage/SETUP.cfg
src/zope/app/zptpage/__init__.py
src/zope/app/zptpage/configure.zcml
src/zope/app/zptpage/ftesting.zcml
src/zope/app/zptpage/i18n.py
src/zope/app/zptpage/interfaces.py
src/zope/app/zptpage/testing.py
src/zope/app/zptpage/zptpage-configure.zcml
src/zope/app/zptpage/zptpage.py
src/zope/app/zptpage/browser/__init__.py
src/zope/app/zptpage/browser/collector266.txt
src/zope/app/zptpage/browser/collector269.txt
src/zope/app/zptpage/browser/configure.zcml
src/zope/app/zptpage/browser/inlinecode.pt
src/zope/app/zptpage/browser/preview.pt
src/zope/app/zptpage/browser/tests.py
src/zope/app/zptpage/browser/url.txt
src/zope/app/zptpage/browser/zpt.gif
src/zope/app/zptpage/browser/zptpage.py
src/zope/app/zptpage/tests/__init__.py
src/zope/app/zptpage/tests/test_zptpage.py
src/zope/app/zptpage/tests/test_zptpageeval.py
src/zope/app/zptpage/textindex/DEPENDENCIES.cfg
src/zope/app/zptpage/textindex/SETUP.cfg
src/zope/app/zptpage/textindex/__init__.py
src/zope/app/zptpage/textindex/configure.zcml
src/zope/app/zptpage/textindex/tests.py
src/zope/app/zptpage/textindex/zope.app.zptpage.textindex-configure.zcml
src/zope/app/zptpage/textindex/zptpage.py